plastron/messaging/__init__.py
plastron/messaging/broker.py
plastron/messaging/messages.py
plastron_messaging-4.6.2.dist-info/METADATA
plastron_messaging-4.6.2.dist-info/WHEEL
plastron_messaging-4.6.2.dist-info/top_level.txt
plastron_messaging-4.6.2.dist-info/RECORD
